LICENSE
sprite_unpack/__init__.py
sprite_unpack/cli.py
sprite_unpack/image.py
sprite_unpack/image_boxes.py
sprite_unpack/sprite_sheet.py
sprite_unpack/types.py
sprite_unpack/unpack.py
sprite_unpack-0.1.1.dist-info/entry_points.txt
sprite_unpack-0.1.1.dist-info/LICENSE
sprite_unpack-0.1.1.dist-info/WHEEL
sprite_unpack-0.1.1.dist-info/METADATA
sprite_unpack-0.1.1.dist-info/RECORD
